{
    "name": true,
    "dicts": "ως-ωτος ώς-ῶτος ώς-ωτός ῶς-ωτός",
    "gend": "masc fem neut",
    "flexes": {
        "sg.nom": "ως ώς ῶς",
        "sg.gen": "ωτος ῶτος ωτός",
        "sg.dat": "ωτι ῶτι ωτί",
        "sg.acc": "ωτα ῶτα ῶς",
        "sg.voc": "ως ώς ῶς",
        "du.nom": "ωτε ῶτε",
        "du.gen": "ώτοιν ώτοιν ωτοῖν",
        "du.dat": "ώτοιν ώτοιν ωτοῖν",
        "du.acc": "ωτε ῶτε",
        "du.voc": "ωτε ῶτε",
        "pl.nom": "ωτες ῶτες ῶτα",
        "pl.gen": "ώτων ωτῶν",
        "pl.dat": "ωσι ωσιν ῶσι ῶσιν ωσί ωσίν",
        "pl.acc": "ωτας ῶτας ῶτα",
        "pl.voc": "ωτες ῶτες ῶτα"
    }
}
