{
  "name": true,
  "masc": "ος-ου ος-οιο ός-οῦ ος-α-ον ός-ά-όν ος-η-ον ός-ή-όν",
  "masc-fem": "ος-ον ός-όν",
  "com _NB!": "нужно разнести ox и не-ox - αἰθαλός - αἴθαλος",
  "flexes": {
        "sg.nom": "ος ός",
        "sg.gen": "ου οιο οῦ",
        "sg.dat": "ῳ ι ῷ",
        "sg.acc": "ον α όν",
        "sg.voc": "ε έ",
        "du.nom": "ω ώ",
        "du.gen": "οιν οῖν",
        "du.dat": "οιν οῖν",
        "du.acc": "ω ώ",
        "du.voc": "ω ώ",
        "pl.nom": "οι οί",
        "pl.gen": "ων ῶν",
        "pl.dat": "οις οισιν οῖς",
        "pl.acc": "ους ούς",
        "pl.voc": "οι οί"
    }
}
