{
    "pos":"name",
    "descr": "cons",
    "var": "eis",
    "gend": "neut",
    "dict": "εις",
    "flexes":{
        "sg.nom": "εν",
        "sg.gen": "εντος",
        "sg.dat": "εντι",
        "sg.acc": "εν",
        "sg.voc": "εν",
        "du.nom": "εντε",
        "du.gen": "έντοιν",
        "du.dat": "έντοιν",
        "du.acc": "εντε",
        "du.voc": "εντε",
        "pl.nom": "εντα",
        "pl.gen": "έντων",
        "pl.dat": "εσι",
        "pl.acc": "εντα",
        "pl.voc": "εντα"
    }
}
